time_magics.py
time_magics-0.5.1.dist-info/LICENSE
time_magics-0.5.1.dist-info/METADATA
time_magics-0.5.1.dist-info/WHEEL
time_magics-0.5.1.dist-info/top_level.txt
time_magics-0.5.1.dist-info/RECORD
