Metadata-Version: 2.1
Name: time-magics
Version: 0.5.1
Summary: iPython %time and %timeit magic command in normal Python files
Home-page: https://github.com/hakonmh/time-magics
Author: Håkon Magne Holmen
Author-email: haakonholmen@hotmail.com
License: MIT
Classifier: Development Status :: 3 - Alpha
Classifier: License :: OSI Approved :: MIT License
Classifier: Programming Language :: Python :: 3.5
Classifier: Programming Language :: Python :: 3.6
Classifier: Programming Language :: Python :: 3.7
Classifier: Programming Language :: Python :: 3.8
Classifier: Programming Language :: Python :: 3.9
Classifier: Programming Language :: Python :: 3.10
Classifier: Programming Language :: Python :: 3.11
Requires-Python: >=3.5
License-File: LICENSE
Requires-Dist: ipython
